Task-9/IN2009, Q8/karnaugh.v
`timescale 1ns/1ps

module karnaugh_map_sop(
    input P, Q, R, S,
    output F
);
    // Implement the SOP expression: QS + P'R̅S + PQR + P̅RS + PQ̅R̅
    assign F = (Q & S) | (~P & ~R & S) | (P & Q & R) | (~P & R & S) | (P & ~Q & ~R);
    
    // Alternative representation using gate-level modeling
    /*
    wire term1, term2, term3, term4, term5;
    and(term1, Q, S);
    and(term2, ~P, ~R, S);
    and(term3, P, Q, R);
    and(term4, ~P, R, S);
    and(term5, P, ~Q, ~R);
    or(F, term1, term2, term3, term4, term5);
    */
endmodule

Task-9/IN2009, Q8/testbench.v
`timescale 1ns/1ps

module tb_karnaugh_map();
    reg P, Q, R, S;
    wire F;
    
    // Instantiate the unit under test
    karnaugh_map_sop uut(
        .P(P),
        .Q(Q),
        .R(R),
        .S(S),
        .F(F)
    );
    
    initial begin
        // Print header with SOP expression
        $display("\nVerification of Karnaugh Map Implementation");
        $display("----------------------------------------");
        $display("Option A: F = QS + P'R̅S + PQR + P̅RS + PQ̅R̅");
        $display("\nTime(ns)  P Q R S | F");
        $display("------------------|---");
        
        // Test all 16 possible input combinations
        // Row 1: P=0, Q=0
        {P, Q, R, S} = 4'b0000; #10;
        $display("%7d   %b %b %b %b |  %b", $time, P, Q, R, S, F);
        {P, Q, R, S} = 4'b0001; #10;
        $display("%7d   %b %b %b %b |  %b", $time, P, Q, R, S, F);
        {P, Q, R, S} = 4'b0010; #10;
        $display("%7d   %b %b %b %b |  %b", $time, P, Q, R, S, F);
        {P, Q, R, S} = 4'b0011; #10;
        $display("%7d   %b %b %b %b |  %b", $time, P, Q, R, S, F);
        
        // Row 2: P=0, Q=1
        {P, Q, R, S} = 4'b0100; #10;
        $display("%7d   %b %b %b %b |  %b", $time, P, Q, R, S, F);
        {P, Q, R, S} = 4'b0101; #10;
        $display("%7d   %b %b %b %b |  %b", $time, P, Q, R, S, F);
        {P, Q, R, S} = 4'b0110; #10;
        $display("%7d   %b %b %b %b |  %b", $time, P, Q, R, S, F);
        {P, Q, R, S} = 4'b0111; #10;
        $display("%7d   %b %b %b %b |  %b", $time, P, Q, R, S, F);
        
        // Row 3: P=1, Q=0
        {P, Q, R, S} = 4'b1000; #10;
        $display("%7d   %b %b %b %b |  %b", $time, P, Q, R, S, F);
        {P, Q, R, S} = 4'b1001; #10;
        $display("%7d   %b %b %b %b |  %b", $time, P, Q, R, S, F);
        {P, Q, R, S} = 4'b1010; #10;
        $display("%7d   %b %b %b %b |  %b", $time, P, Q, R, S, F);
        {P, Q, R, S} = 4'b1011; #10;
        $display("%7d   %b %b %b %b |  %b", $time, P, Q, R, S, F);
        
        // Row 4: P=1, Q=1
        {P, Q, R, S} = 4'b1100; #10;
        $display("%7d   %b %b %b %b |  %b", $time, P, Q, R, S, F);
        {P, Q, R, S} = 4'b1101; #10;
        $display("%7d   %b %b %b %b |  %b", $time, P, Q, R, S, F);
        {P, Q, R, S} = 4'b1110; #10;
        $display("%7d   %b %b %b %b |  %b", $time, P, Q, R, S, F);
        {P, Q, R, S} = 4'b1111; #10;
        $display("%7d   %b %b %b %b |  %b", $time, P, Q, R, S, F);
        
        $display("\nVerification complete!");
        $finish;
    end
    
    // Optional: Create VCD file for waveform viewing
    initial begin
        $dumpfile("karnaugh_wave.vcd");
        $dumpvars(0, tb_karnaugh_map);
    end
endmodule

Task-9/IN2009, Q8/karnaugh_wave.vcd
$date
	Wed May  7 13:15:20 2025
$end
$version
	Icarus Verilog
$end
$timescale
	1ps
$end
$scope module tb_karnaugh_map $end
$var wire 1 ! F $end
$var reg 1 " P $end
$var reg 1 # Q $end
$var reg 1 $ R $end
$var reg 1 % S $end
$scope module uut $end
$var wire 1 ! F $end
$var wire 1 " P $end
$var wire 1 # Q $end
$var wire 1 $ R $end
$var wire 1 % S $end
$upscope $end
$upscope $end
$enddefinitions $end
#0
$dumpvars
0%
0$
0#
0"
0!
$end
#10000
1!
1%
#20000
0!
1$
0%
#30000
1!
1%
#40000
0!
1#
0$
0%
#50000
1!
1%
#60000
0!
1$
0%
#70000
1!
1%
#80000
1"
0#
0$
0%
#90000
1%
#100000
0!
1$
0%
#110000
1%
#120000
0!
1#
0$
0%
#130000
1!
1%
#140000
1$
0%
#150000
1%
